{
  "info": {
    "_postman_id": "mo-marketplace-api-collection",
    "name": "MO Marketplace API",
    "description": "Complete API collection for MO Marketplace Backend - All endpoints with authentication and examples",
    "schema": "https://schema.getpostman.com/json/collection/v2.1.0/collection.json"
  },
  "item": [
    {
      "name": "🔐 Authentication",
      "item": [
        {
          "name": "Register User",
          "request": {
            "method": "POST",
            "header": [
              {
                "key": "Content-Type",
                "value": "application/json"
              }
            ],
            "body": {
              "mode": "raw",
              "raw": "{\n  \"name\": \"John Doe\",\n  \"email\": \"john@example.com\",\n  \"password\": \"SecurePass123\"\n}"
            },
            "url": {
              "raw": "{{base_url}}/auth/register",
              "host": [
                "{{base_url}}"
              ],
              "path": [
                "auth",
                "register"
              ]
            },
            "description": "Register a new user account. Password must be at least 6 characters."
          },
          "response": []
        },
        {
          "name": "Login User",
          "request": {
            "method": "POST",
            "header": [
              {
                "key": "Content-Type",
                "value": "application/json"
              }
            ],
            "body": {
              "mode": "raw",
              "raw": "{\n  \"email\": \"john@example.com\",\n  \"password\": \"SecurePass123\"\n}"
            },
            "url": {
              "raw": "{{base_url}}/auth/login",
              "host": [
                "{{base_url}}"
              ],
              "path": [
                "auth",
                "login"
              ]
            },
            "description": "Login with email and password. Returns JWT access token."
          },
          "response": []
        },
        {
          "name": "Get User Profile",
          "request": {
            "method": "POST",
            "header": [
              {
                "key": "Authorization",
                "value": "Bearer {{jwt_token}}",
                "type": "text"
              },
              {
                "key": "Content-Type",
                "value": "application/json"
              }
            ],
            "url": {
              "raw": "{{base_url}}/auth/profile",
              "host": [
                "{{base_url}}"
              ],
              "path": [
                "auth",
                "profile"
              ]
            },
            "description": "Get currently authenticated user profile. Requires JWT token."
          },
          "response": []
        },
        {
          "name": "Create Admin User",
          "request": {
            "method": "POST",
            "header": [
              {
                "key": "Authorization",
                "value": "Bearer {{jwt_token}}",
                "type": "text"
              },
              {
                "key": "Content-Type",
                "value": "application/json"
              }
            ],
            "body": {
              "mode": "raw",
              "raw": "{\n  \"email\": \"admin2@example.com\",\n  \"password\": \"AdminPassword123\"\n}"
            },
            "url": {
              "raw": "{{base_url}}/auth/admin/create",
              "host": [
                "{{base_url}}"
              ],
              "path": [
                "auth",
                "admin",
                "create"
              ]
            },
            "description": "Create a new admin user. Admin only. Requires JWT token with admin role."
          },
          "response": []
        }
      ]
    },
    {
      "name": "🛍️ Products - Public",
      "item": [
        {
          "name": "Get All Products",
          "request": {
            "method": "GET",
            "header": [
              {
                "key": "Content-Type",
                "value": "application/json"
              }
            ],
            "url": {
              "raw": "{{base_url}}/products",
              "host": [
                "{{base_url}}"
              ],
              "path": [
                "products"
              ]
            },
            "description": "Get all available products. No authentication required."
          },
          "response": []
        },
        {
          "name": "Get Product Variants",
          "request": {
            "method": "GET",
            "header": [
              {
                "key": "Content-Type",
                "value": "application/json"
              }
            ],
            "url": {
              "raw": "{{base_url}}/products/1/variants",
              "host": [
                "{{base_url}}"
              ],
              "path": [
                "products",
                "1",
                "variants"
              ]
            },
            "description": "Get all variants for a specific product by product ID. No authentication required."
          },
          "response": []
        },
        {
          "name": "Get Product Attributes (for filtering)",
          "request": {
            "method": "GET",
            "header": [
              {
                "key": "Content-Type",
                "value": "application/json"
              }
            ],
            "url": {
              "raw": "{{base_url}}/products/1/attributes",
              "host": [
                "{{base_url}}"
              ],
              "path": [
                "products",
                "1",
                "attributes"
              ]
            },
            "description": "Get all available attributes for filtering a product's variants. No authentication required."
          },
          "response": []
        },
        {
          "name": "Filter Product Variants",
          "request": {
            "method": "POST",
            "header": [
              {
                "key": "Content-Type",
                "value": "application/json"
              }
            ],
            "body": {
              "mode": "raw",
              "raw": "{\n  \"attributeValueIds\": [1, 3]\n}"
            },
            "url": {
              "raw": "{{base_url}}/products/1/variants/filter",
              "host": [
                "{{base_url}}"
              ],
              "path": [
                "products",
                "1",
                "variants",
                "filter"
              ]
            },
            "description": "Filter variants by selected attribute values. No authentication required."
          },
          "response": []
        }
      ]
    },
    {
      "name": "📦 Products - Admin",
      "item": [
        {
          "name": "Create Product",
          "request": {
            "method": "POST",
            "header": [
              {
                "key": "Authorization",
                "value": "Bearer {{jwt_token}}",
                "type": "text"
              },
              {
                "key": "Content-Type",
                "value": "application/json"
              }
            ],
            "body": {
              "mode": "raw",
              "raw": "{\n  \"name\": \"T-Shirt\",\n  \"description\": \"Comfortable cotton t-shirt\"\n}"
            },
            "url": {
              "raw": "{{base_url}}/admin/products",
              "host": [
                "{{base_url}}"
              ],
              "path": [
                "admin",
                "products"
              ]
            },
            "description": "Create a new product. Admin only. Requires JWT token."
          },
          "response": []
        },
        {
          "name": "Update Product",
          "request": {
            "method": "PATCH",
            "header": [
              {
                "key": "Authorization",
                "value": "Bearer {{jwt_token}}",
                "type": "text"
              },
              {
                "key": "Content-Type",
                "value": "application/json"
              }
            ],
            "body": {
              "mode": "raw",
              "raw": "{\n  \"name\": \"Updated T-Shirt\",\n  \"description\": \"Premium quality cotton t-shirt\"\n}"
            },
            "url": {
              "raw": "{{base_url}}/admin/products/1",
              "host": [
                "{{base_url}}"
              ],
              "path": [
                "admin",
                "products",
                "1"
              ]
            },
            "description": "Update an existing product. Admin only. Requires JWT token."
          },
          "response": []
        },
        {
          "name": "Delete Product",
          "request": {
            "method": "DELETE",
            "header": [
              {
                "key": "Authorization",
                "value": "Bearer {{jwt_token}}",
                "type": "text"
              },
              {
                "key": "Content-Type",
                "value": "application/json"
              }
            ],
            "url": {
              "raw": "{{base_url}}/admin/products/1",
              "host": [
                "{{base_url}}"
              ],
              "path": [
                "admin",
                "products",
                "1"
              ]
            },
            "description": "Delete a product and all its variants. Admin only. Requires JWT token."
          },
          "response": []
        },
        {
          "name": "Create Product Variant",
          "request": {
            "method": "POST",
            "header": [
              {
                "key": "Authorization",
                "value": "Bearer {{jwt_token}}",
                "type": "text"
              },
              {
                "key": "Content-Type",
                "value": "application/json"
              }
            ],
            "body": {
              "mode": "raw",
              "raw": "{\n  \"price\": 29.99,\n  \"stock\": 100,\n  \"attributeValueIds\": [1, 3, 5]\n}"
            },
            "url": {
              "raw": "{{base_url}}/admin/products/1/variants",
              "host": [
                "{{base_url}}"
              ],
              "path": [
                "admin",
                "products",
                "1",
                "variants"
              ]
            },
            "description": "Create a new variant for a product with specific attributes, price, and stock. Admin only."
          },
          "response": []
        },
        {
          "name": "Update Product Variant",
          "request": {
            "method": "PATCH",
            "header": [
              {
                "key": "Authorization",
                "value": "Bearer {{jwt_token}}",
                "type": "text"
              },
              {
                "key": "Content-Type",
                "value": "application/json"
              }
            ],
            "body": {
              "mode": "raw",
              "raw": "{\n  \"stock\": 75\n}"
            },
            "url": {
              "raw": "{{base_url}}/admin/products/1/variants/1",
              "host": [
                "{{base_url}}"
              ],
              "path": [
                "admin",
                "products",
                "1",
                "variants",
                "1"
              ]
            },
            "description": "Update variant stock level. Admin only. Requires JWT token."
          },
          "response": []
        },
        {
          "name": "Delete Product Variant",
          "request": {
            "method": "DELETE",
            "header": [
              {
                "key": "Authorization",
                "value": "Bearer {{jwt_token}}",
                "type": "text"
              },
              {
                "key": "Content-Type",
                "value": "application/json"
              }
            ],
            "url": {
              "raw": "{{base_url}}/admin/products/1/variants/1",
              "host": [
                "{{base_url}}"
              ],
              "path": [
                "admin",
                "products",
                "1",
                "variants",
                "1"
              ]
            },
            "description": "Delete a product variant. Admin only. Requires JWT token."
          },
          "response": []
        }
      ]
    },
    {
      "name": "🎨 Attributes - Admin",
      "item": [
        {
          "name": "Create Attribute",
          "request": {
            "method": "POST",
            "header": [
              {
                "key": "Authorization",
                "value": "Bearer {{jwt_token}}",
                "type": "text"
              },
              {
                "key": "Content-Type",
                "value": "application/json"
              }
            ],
            "body": {
              "mode": "raw",
              "raw": "{\n  \"name\": \"Color\"\n}"
            },
            "url": {
              "raw": "{{base_url}}/admin/attributes",
              "host": [
                "{{base_url}}"
              ],
              "path": [
                "admin",
                "attributes"
              ]
            },
            "description": "Create a new product attribute (e.g., Color, Size, Material). Admin only."
          },
          "response": []
        },
        {
          "name": "Get All Attributes",
          "request": {
            "method": "GET",
            "header": [
              {
                "key": "Authorization",
                "value": "Bearer {{jwt_token}}",
                "type": "text"
              },
              {
                "key": "Content-Type",
                "value": "application/json"
              }
            ],
            "url": {
              "raw": "{{base_url}}/admin/attributes",
              "host": [
                "{{base_url}}"
              ],
              "path": [
                "admin",
                "attributes"
              ]
            },
            "description": "Get all available product attributes. Admin only."
          },
          "response": []
        },
        {
          "name": "Create Attribute Value",
          "request": {
            "method": "POST",
            "header": [
              {
                "key": "Authorization",
                "value": "Bearer {{jwt_token}}",
                "type": "text"
              },
              {
                "key": "Content-Type",
                "value": "application/json"
              }
            ],
            "body": {
              "mode": "raw",
              "raw": "{\n  \"attribute_id\": 1,\n  \"value\": \"Red\"\n}"
            },
            "url": {
              "raw": "{{base_url}}/admin/attributes/values",
              "host": [
                "{{base_url}}"
              ],
              "path": [
                "admin",
                "attributes",
                "values"
              ]
            },
            "description": "Create a new value for an attribute (e.g., 'Red' for Color). Admin only."
          },
          "response": []
        },
        {
          "name": "Get All Attribute Values",
          "request": {
            "method": "GET",
            "header": [
              {
                "key": "Authorization",
                "value": "Bearer {{jwt_token}}",
                "type": "text"
              },
              {
                "key": "Content-Type",
                "value": "application/json"
              }
            ],
            "url": {
              "raw": "{{base_url}}/admin/attributes/values",
              "host": [
                "{{base_url}}"
              ],
              "path": [
                "admin",
                "attributes",
                "values"
              ]
            },
            "description": "Get all attribute values. Admin only."
          },
          "response": []
        },
        {
          "name": "Get Attribute Values by Attribute ID",
          "request": {
            "method": "GET",
            "header": [
              {
                "key": "Authorization",
                "value": "Bearer {{jwt_token}}",
                "type": "text"
              },
              {
                "key": "Content-Type",
                "value": "application/json"
              }
            ],
            "url": {
              "raw": "{{base_url}}/admin/attributes/attribute/1/values",
              "host": [
                "{{base_url}}"
              ],
              "path": [
                "admin",
                "attributes",
                "attribute",
                "1",
                "values"
              ]
            },
            "description": "Get all values for a specific attribute. Admin only."
          },
          "response": []
        },
        {
          "name": "Delete Attribute Value",
          "request": {
            "method": "DELETE",
            "header": [
              {
                "key": "Authorization",
                "value": "Bearer {{jwt_token}}",
                "type": "text"
              },
              {
                "key": "Content-Type",
                "value": "application/json"
              }
            ],
            "url": {
              "raw": "{{base_url}}/admin/attributes/values/1",
              "host": [
                "{{base_url}}"
              ],
              "path": [
                "admin",
                "attributes",
                "values",
                "1"
              ]
            },
            "description": "Delete an attribute value. Admin only."
          },
          "response": []
        },
        {
          "name": "Delete Attribute",
          "request": {
            "method": "DELETE",
            "header": [
              {
                "key": "Authorization",
                "value": "Bearer {{jwt_token}}",
                "type": "text"
              },
              {
                "key": "Content-Type",
                "value": "application/json"
              }
            ],
            "url": {
              "raw": "{{base_url}}/admin/attributes/1",
              "host": [
                "{{base_url}}"
              ],
              "path": [
                "admin",
                "attributes",
                "1"
              ]
            },
            "description": "Delete an attribute and all its values. Admin only."
          },
          "response": []
        }
      ]
    },
    {
      "name": "📋 Orders",
      "item": [
        {
          "name": "Get All Orders",
          "request": {
            "method": "GET",
            "header": [
              {
                "key": "Authorization",
                "value": "Bearer {{jwt_token}}",
                "type": "text"
              },
              {
                "key": "Content-Type",
                "value": "application/json"
              }
            ],
            "url": {
              "raw": "{{base_url}}/orders",
              "host": [
                "{{base_url}}"
              ],
              "path": [
                "orders"
              ]
            },
            "description": "Get all orders with full details including items, products, and variants. Requires JWT token."
          },
          "response": []
        },
        {
          "name": "Create Order",
          "request": {
            "method": "POST",
            "header": [
              {
                "key": "Authorization",
                "value": "Bearer {{jwt_token}}",
                "type": "text"
              },
              {
                "key": "Content-Type",
                "value": "application/json"
              }
            ],
            "body": {
              "mode": "raw",
              "raw": "{\n  \"items\": [\n    {\n      \"product_id\": 1,\n      \"variant_id\": 1,\n      \"quantity\": 2\n    },\n    {\n      \"product_id\": 2,\n      \"variant_id\": 3,\n      \"quantity\": 1\n    }\n  ]\n}"
            },
            "url": {
              "raw": "{{base_url}}/orders",
              "host": [
                "{{base_url}}"
              ],
              "path": [
                "orders"
              ]
            },
            "description": "Create a new order with one or more items. Validates product/variant existence and stock availability. Requires JWT token."
          },
          "response": []
        }
      ]
    }
  ],
  "variable": [
    {
      "key": "base_url",
      "value": "http://localhost:3000",
      "type": "string"
    },
    {
      "key": "jwt_token",
      "value": "",
      "type": "string"
    }
  ]
}
